{"v":"5.7.14","fr":30,"ip":0,"op":46,"w":576,"h":576,"nm":"Eyelash","ddd":0,"assets":[],"layers":[{"ddd":0,"ind":1,"ty":4,"nm":"Layer 9","sr":1,"ks":{"o":{"a":0,"k":100},"r":{"a":1,"k":[{"i":{"x":[0.313],"y":[1]},"o":{"x":[0.333],"y":[0]},"t":2,"s":[0]},{"i":{"x":[0.667],"y":[1]},"o":{"x":[0.641],"y":[0]},"t":14,"s":[6]},{"i":{"x":[0.667],"y":[1]},"o":{"x":[0.333],"y":[0]},"t":26,"s":[-4]},{"i":{"x":[0.667],"y":[1]},"o":{"x":[0.333],"y":[0]},"t":32,"s":[2]},{"t":38,"s":[0]}]},"p":{"a":0,"k":[181.847,460.076,0]},"a":{"a":0,"k":[0,0,0]},"s":{"a":0,"k":[100,100,100]}},"ao":0,"shapes":[{"ty":"gr","it":[{"ind":0,"ty":"sh","ks":{"a":0,"k":{"i":[[8.508,16.191],[0,0],[-16.191,8.508],[0,0],[-2.312,-4.4],[0,0],[4.4,-2.312],[0,0]],"o":[[0,0],[-8.508,-16.191],[0,0],[4.4,-2.312],[0,0],[2.312,4.4],[0,0],[-16.191,8.508]],"v":[[-62.121,34.646],[-62.121,34.646],[-48.21,-10.074],[30.305,-51.33],[42.458,-47.55],[64.894,-4.852],[61.114,7.301],[-17.401,48.558]],"c":true}},"nm":"Path 1","hd":false},{"ty":"st","c":{"a":0,"k":[0.902,0.722,0.592]},"o":{"a":0,"k":100},"w":{"a":0,"k":15},"lc":2,"lj":1,"ml":10,"bm":0,"nm":"Stroke 1","hd":false},{"ty":"tr","p":{"a":0,"k":[0,0]},"a":{"a":0,"k":[0,0]},"s":{"a":0,"k":[100,100]},"r":{"a":0,"k":0},"o":{"a":0,"k":100},"sk":{"a":0,"k":0},"sa":{"a":0,"k":0},"nm":"Transform"}],"nm":"Group 1","bm":0,"hd":false}],"ip":0,"op":46,"st":0,"bm":0},{"ddd":0,"ind":2,"ty":4,"nm":"Layer 16","parent":3,"sr":1,"ks":{"o":{"a":0,"k":100},"r":{"a":0,"k":0},"p":{"a":0,"k":[342.558,376.864,0]},"a":{"a":0,"k":[342.558,376.864,0]},"s":{"a":0,"k":[100,100,100]}},"ao":0,"shapes":[{"ty":"gr","it":[{"ind":0,"ty":"sh","ks":{"a":0,"k":{"i":[[0,0],[0,0]],"o":[[0,0],[0,0]],"v":[[-16.046,-30.537],[16.046,30.537]],"c":false}},"nm":"Path 1","hd":false},{"ty":"st","c":{"a":0,"k":[0.902,0.722,0.592]},"o":{"a":0,"k":100},"w":{"a":0,"k":15},"lc":2,"lj":1,"ml":10,"bm":0,"nm":"Stroke 1","hd":false},{"ty":"tr","p":{"a":0,"k":[302.981,397.66]},"a":{"a":0,"k":[0,0]},"s":{"a":0,"k":[100,100]},"r":{"a":0,"k":0},"o":{"a":0,"k":100},"sk":{"a":0,"k":0},"sa":{"a":0,"k":0},"nm":"Transform"}],"nm":"Group 1","bm":0,"hd":false},{"ty":"gr","it":[{"ind":0,"ty":"sh","ks":{"a":0,"k":{"i":[[0,0],[0,0]],"o":[[0,0],[0,0]],"v":[[-16.046,-30.537],[16.046,30.537]],"c":false}},"nm":"Path 1","hd":false},{"ty":"st","c":{"a":0,"k":[0.902,0.722,0.592]},"o":{"a":0,"k":100},"w":{"a":0,"k":15},"lc":2,"lj":1,"ml":10,"bm":0,"nm":"Stroke 1","hd":false},{"ty":"tr","p":{"a":0,"k":[342.558,376.864]},"a":{"a":0,"k":[0,0]},"s":{"a":0,"k":[100,100]},"r":{"a":0,"k":0},"o":{"a":0,"k":100},"sk":{"a":0,"k":0},"sa":{"a":0,"k":0},"nm":"Transform"}],"nm":"Group 2","bm":0,"hd":false},{"ty":"gr","it":[{"ind":0,"ty":"sh","ks":{"a":0,"k":{"i":[[0,0],[0,0]],"o":[[0,0],[0,0]],"v":[[-16.046,-30.537],[16.046,30.537]],"c":false}},"nm":"Path 1","hd":false},{"ty":"st","c":{"a":0,"k":[0.902,0.722,0.592]},"o":{"a":0,"k":100},"w":{"a":0,"k":15},"lc":2,"lj":1,"ml":10,"bm":0,"nm":"Stroke 1","hd":false},{"ty":"tr","p":{"a":0,"k":[382.134,356.069]},"a":{"a":0,"k":[0,0]},"s":{"a":0,"k":[100,100]},"r":{"a":0,"k":0},"o":{"a":0,"k":100},"sk":{"a":0,"k":0},"sa":{"a":0,"k":0},"nm":"Transform"}],"nm":"Group 3","bm":0,"hd":false},{"ty":"gr","it":[{"ind":0,"ty":"sh","ks":{"a":0,"k":{"i":[[0,0],[0,0]],"o":[[0,0],[0,0]],"v":[[72.19,-37.933],[-72.19,37.933]],"c":false}},"nm":"Path 1","hd":false},{"ty":"st","c":{"a":0,"k":[0.902,0.722,0.592]},"o":{"a":0,"k":100},"w":{"a":0,"k":15},"lc":2,"lj":1,"ml":10,"bm":0,"nm":"Stroke 1","hd":false},{"ty":"tr","p":{"a":0,"k":[342.558,376.864]},"a":{"a":0,"k":[0,0]},"s":{"a":0,"k":[100,100]},"r":{"a":0,"k":0},"o":{"a":0,"k":100},"sk":{"a":0,"k":0},"sa":{"a":0,"k":0},"nm":"Transform"}],"nm":"Group 4","bm":0,"hd":false},{"ty":"tm","s":{"a":0,"k":0},"e":{"a":1,"k":[{"i":{"x":[0.667],"y":[1]},"o":{"x":[0.167],"y":[0.167]},"t":9,"s":[0]},{"t":22,"s":[100]}]},"o":{"a":0,"k":0},"m":1,"nm":"Trim Paths 1","hd":false}],"ip":6,"op":46,"st":0,"bm":0},{"ddd":0,"ind":3,"ty":4,"nm":"Layer 8","parent":1,"sr":1,"ks":{"o":{"a":0,"k":100},"r":{"a":1,"k":[{"i":{"x":[0.313],"y":[1]},"o":{"x":[0.333],"y":[0]},"t":0,"s":[0]},{"i":{"x":[0.667],"y":[1]},"o":{"x":[0.641],"y":[0]},"t":12,"s":[6]},{"i":{"x":[0.667],"y":[1]},"o":{"x":[0.333],"y":[0]},"t":24,"s":[-4]},{"i":{"x":[0.667],"y":[1]},"o":{"x":[0.333],"y":[0]},"t":30,"s":[2]},{"t":36,"s":[0]}]},"p":{"a":0,"k":[88.52,-45.278,0]},"a":{"a":0,"k":[270.367,414.798,0]},"s":{"a":0,"k":[100,100,100]}},"ao":0,"shapes":[{"ty":"gr","it":[{"ind":0,"ty":"sh","ks":{"a":0,"k":{"i":[[0,0],[0,0]],"o":[[0,0],[0,0]],"v":[[-16.046,-30.537],[16.046,30.537]],"c":false}},"nm":"Path 1","hd":false},{"ty":"st","c":{"a":0,"k":[0.902,0.722,0.592]},"o":{"a":0,"k":100},"w":{"a":0,"k":15},"lc":2,"lj":1,"ml":10,"bm":0,"nm":"Stroke 1","hd":false},{"ty":"tr","p":{"a":0,"k":[302.981,397.66]},"a":{"a":0,"k":[0,0]},"s":{"a":0,"k":[100,100]},"r":{"a":0,"k":0},"o":{"a":0,"k":100},"sk":{"a":0,"k":0},"sa":{"a":0,"k":0},"nm":"Transform"}],"nm":"Group 1","bm":0,"hd":false},{"ty":"gr","it":[{"ind":0,"ty":"sh","ks":{"a":0,"k":{"i":[[0,0],[0,0]],"o":[[0,0],[0,0]],"v":[[-16.046,-30.537],[16.046,30.537]],"c":false}},"nm":"Path 1","hd":false},{"ty":"st","c":{"a":0,"k":[0.902,0.722,0.592]},"o":{"a":0,"k":100},"w":{"a":0,"k":15},"lc":2,"lj":1,"ml":10,"bm":0,"nm":"Stroke 1","hd":false},{"ty":"tr","p":{"a":0,"k":[342.558,376.864]},"a":{"a":0,"k":[0,0]},"s":{"a":0,"k":[100,100]},"r":{"a":0,"k":0},"o":{"a":0,"k":100},"sk":{"a":0,"k":0},"sa":{"a":0,"k":0},"nm":"Transform"}],"nm":"Group 2","bm":0,"hd":false},{"ty":"gr","it":[{"ind":0,"ty":"sh","ks":{"a":0,"k":{"i":[[0,0],[0,0]],"o":[[0,0],[0,0]],"v":[[-16.046,-30.537],[16.046,30.537]],"c":false}},"nm":"Path 1","hd":false},{"ty":"st","c":{"a":0,"k":[0.902,0.722,0.592]},"o":{"a":0,"k":100},"w":{"a":0,"k":15},"lc":2,"lj":1,"ml":10,"bm":0,"nm":"Stroke 1","hd":false},{"ty":"tr","p":{"a":0,"k":[382.134,356.069]},"a":{"a":0,"k":[0,0]},"s":{"a":0,"k":[100,100]},"r":{"a":0,"k":0},"o":{"a":0,"k":100},"sk":{"a":0,"k":0},"sa":{"a":0,"k":0},"nm":"Transform"}],"nm":"Group 3","bm":0,"hd":false},{"ty":"gr","it":[{"ind":0,"ty":"sh","ks":{"a":0,"k":{"i":[[0,0],[0,0]],"o":[[0,0],[0,0]],"v":[[72.19,-37.933],[-72.19,37.933]],"c":false}},"nm":"Path 1","hd":false},{"ty":"st","c":{"a":0,"k":[0.902,0.722,0.592]},"o":{"a":0,"k":100},"w":{"a":0,"k":15},"lc":2,"lj":1,"ml":10,"bm":0,"nm":"Stroke 1","hd":false},{"ty":"tr","p":{"a":0,"k":[342.558,376.864]},"a":{"a":0,"k":[0,0]},"s":{"a":0,"k":[100,100]},"r":{"a":0,"k":0},"o":{"a":0,"k":100},"sk":{"a":0,"k":0},"sa":{"a":0,"k":0},"nm":"Transform"}],"nm":"Group 4","bm":0,"hd":false},{"ty":"tm","s":{"a":1,"k":[{"i":{"x":[0.833],"y":[0.833]},"o":{"x":[0.333],"y":[0]},"t":0,"s":[0]},{"t":16,"s":[100]}]},"e":{"a":0,"k":100},"o":{"a":0,"k":0},"m":1,"nm":"Trim Paths 1","hd":false}],"ip":0,"op":46,"st":0,"bm":0},{"ddd":0,"ind":4,"ty":4,"nm":"Layer 7","sr":1,"ks":{"o":{"a":0,"k":100},"r":{"a":0,"k":0},"p":{"a":0,"k":[287.992,183.177,0]},"a":{"a":0,"k":[0,0,0]},"s":{"a":0,"k":[100,100,100]}},"ao":0,"shapes":[{"ty":"gr","it":[{"ind":0,"ty":"sh","ks":{"a":1,"k":[{"i":{"x":0.251,"y":1},"o":{"x":0.333,"y":0},"t":0,"s":[{"i":[[0,0],[88.008,0],[7.991,31.098]],"o":[[-18.974,37.098],[-89.492,0],[0,0]],"v":[[169.982,-56.775],[0,56.775],[-169.982,-56.775]],"c":false}]},{"i":{"x":0.667,"y":1},"o":{"x":0.792,"y":0},"t":10,"s":[{"i":[[0,0],[88.008,0],[7.991,31.098]],"o":[[-18.974,37.098],[-89.492,0],[0,0]],"v":[[169.982,-56.775],[0,21.725],[-169.982,-56.775]],"c":false}]},{"t":20,"s":[{"i":[[0,0],[88.008,0],[7.991,31.098]],"o":[[-18.974,37.098],[-89.492,0],[0,0]],"v":[[169.982,-56.775],[0,56.775],[-169.982,-56.775]],"c":false}]}]},"nm":"Path 1","hd":false},{"ty":"st","c":{"a":0,"k":[0.4,0.561,0.518]},"o":{"a":0,"k":100},"w":{"a":0,"k":15},"lc":2,"lj":2,"bm":0,"nm":"Stroke 1","hd":false},{"ty":"tr","p":{"a":0,"k":[0,0]},"a":{"a":0,"k":[0,0]},"s":{"a":0,"k":[100,100]},"r":{"a":0,"k":0},"o":{"a":0,"k":100},"sk":{"a":0,"k":0},"sa":{"a":0,"k":0},"nm":"Transform"}],"nm":"Group 1","bm":0,"hd":false}],"ip":0,"op":46,"st":0,"bm":0},{"ddd":0,"ind":5,"ty":4,"nm":"Layer 15","sr":1,"ks":{"o":{"a":0,"k":100},"r":{"a":0,"k":0},"p":{"a":0,"k":[92.4,137.015,0]},"a":{"a":0,"k":[0,0,0]},"s":{"a":0,"k":[100,100,100]}},"ao":0,"shapes":[{"ty":"gr","it":[{"ind":0,"ty":"sh","ks":{"a":0,"k":{"i":[[0,0],[0,0]],"o":[[0,0],[0,0]],"v":[[25.609,-10.613],[-25.609,10.613]],"c":false}},"nm":"Path 1","hd":false},{"ty":"st","c":{"a":0,"k":[0.4,0.561,0.518]},"o":{"a":0,"k":100},"w":{"a":0,"k":15},"lc":2,"lj":2,"bm":0,"nm":"Stroke 1","hd":false},{"ty":"tr","p":{"a":0,"k":[0,0]},"a":{"a":0,"k":[0,0]},"s":{"a":0,"k":[100,100]},"r":{"a":0,"k":0},"o":{"a":0,"k":100},"sk":{"a":0,"k":0},"sa":{"a":0,"k":0},"nm":"Transform"}],"nm":"Group 1","bm":0,"hd":false},{"ty":"tm","s":{"a":0,"k":0},"e":{"a":1,"k":[{"i":{"x":[0.667],"y":[1]},"o":{"x":[0.167],"y":[0.167]},"t":6,"s":[0]},{"t":16,"s":[100]}]},"o":{"a":0,"k":0},"m":1,"nm":"Trim Paths 1","hd":false}],"ip":6,"op":46,"st":0,"bm":0},{"ddd":0,"ind":6,"ty":4,"nm":"Layer 14","sr":1,"ks":{"o":{"a":0,"k":100},"r":{"a":0,"k":0},"p":{"a":0,"k":[483.554,137.001,0]},"a":{"a":0,"k":[0,0,0]},"s":{"a":0,"k":[100,100,100]}},"ao":0,"shapes":[{"ty":"gr","it":[{"ind":0,"ty":"sh","ks":{"a":0,"k":{"i":[[0,0],[0,0]],"o":[[0,0],[0,0]],"v":[[25.58,10.599],[-25.58,-10.599]],"c":false}},"nm":"Path 1","hd":false},{"ty":"st","c":{"a":0,"k":[0.4,0.561,0.518]},"o":{"a":0,"k":100},"w":{"a":0,"k":15},"lc":2,"lj":2,"bm":0,"nm":"Stroke 1","hd":false},{"ty":"tr","p":{"a":0,"k":[0,0]},"a":{"a":0,"k":[0,0]},"s":{"a":0,"k":[100,100]},"r":{"a":0,"k":0},"o":{"a":0,"k":100},"sk":{"a":0,"k":0},"sa":{"a":0,"k":0},"nm":"Transform"}],"nm":"Group 1","bm":0,"hd":false},{"ty":"tm","s":{"a":0,"k":0},"e":{"a":1,"k":[{"i":{"x":[0.667],"y":[1]},"o":{"x":[0.167],"y":[0.167]},"t":6,"s":[0]},{"t":16,"s":[100]}]},"o":{"a":0,"k":0},"m":1,"nm":"Trim Paths 1","hd":false}],"ip":6,"op":46,"st":0,"bm":0},{"ddd":0,"ind":7,"ty":4,"nm":"Layer 13","sr":1,"ks":{"o":{"a":0,"k":100},"r":{"a":0,"k":0},"p":{"a":1,"k":[{"i":{"x":0.251,"y":1},"o":{"x":0.333,"y":0},"t":0,"s":[206.982,251.568,0],"to":[0,-3.833,0],"ti":[0,0,0]},{"i":{"x":0.667,"y":1},"o":{"x":0.792,"y":0},"t":10,"s":[206.982,228.568,0],"to":[0,0,0],"ti":[0,-3.833,0]},{"t":20,"s":[206.982,251.568,0]}]},"a":{"a":0,"k":[0,0,0]},"s":{"a":0,"k":[100,100,100]}},"ao":0,"shapes":[{"ty":"gr","it":[{"ind":0,"ty":"sh","ks":{"a":0,"k":{"i":[[0,0],[0,0]],"o":[[0,0],[0,0]],"v":[[10.599,-25.595],[-10.599,25.595]],"c":false}},"nm":"Path 1","hd":false},{"ty":"st","c":{"a":0,"k":[0.4,0.561,0.518]},"o":{"a":0,"k":100},"w":{"a":0,"k":15},"lc":2,"lj":2,"bm":0,"nm":"Stroke 1","hd":false},{"ty":"tr","p":{"a":0,"k":[0,0]},"a":{"a":0,"k":[0,0]},"s":{"a":0,"k":[100,100]},"r":{"a":0,"k":0},"o":{"a":0,"k":100},"sk":{"a":0,"k":0},"sa":{"a":0,"k":0},"nm":"Transform"}],"nm":"Group 1","bm":0,"hd":false},{"ty":"tm","s":{"a":0,"k":0},"e":{"a":1,"k":[{"i":{"x":[0.667],"y":[1]},"o":{"x":[0.167],"y":[0.167]},"t":6,"s":[0]},{"t":16,"s":[100]}]},"o":{"a":0,"k":0},"m":1,"nm":"Trim Paths 1","hd":false}],"ip":6,"op":46,"st":0,"bm":0},{"ddd":0,"ind":8,"ty":4,"nm":"Layer 12","sr":1,"ks":{"o":{"a":0,"k":100},"r":{"a":0,"k":0},"p":{"a":1,"k":[{"i":{"x":0.251,"y":1},"o":{"x":0.333,"y":0},"t":0,"s":[369.001,251.554,0],"to":[0,-3.833,0],"ti":[0,0,0]},{"i":{"x":0.667,"y":1},"o":{"x":0.792,"y":0},"t":10,"s":[369.001,228.554,0],"to":[0,0,0],"ti":[0,-3.833,0]},{"t":20,"s":[369.001,251.554,0]}]},"a":{"a":0,"k":[0,0,0]},"s":{"a":0,"k":[100,100,100]}},"ao":0,"shapes":[{"ty":"gr","it":[{"ind":0,"ty":"sh","ks":{"a":0,"k":{"i":[[0,0],[0,0]],"o":[[0,0],[0,0]],"v":[[10.599,25.58],[-10.599,-25.58]],"c":false}},"nm":"Path 1","hd":false},{"ty":"st","c":{"a":0,"k":[0.4,0.561,0.518]},"o":{"a":0,"k":100},"w":{"a":0,"k":15},"lc":2,"lj":2,"bm":0,"nm":"Stroke 1","hd":false},{"ty":"tr","p":{"a":0,"k":[0,0]},"a":{"a":0,"k":[0,0]},"s":{"a":0,"k":[100,100]},"r":{"a":0,"k":0},"o":{"a":0,"k":100},"sk":{"a":0,"k":0},"sa":{"a":0,"k":0},"nm":"Transform"}],"nm":"Group 1","bm":0,"hd":false},{"ty":"tm","s":{"a":0,"k":0},"e":{"a":1,"k":[{"i":{"x":[0.667],"y":[1]},"o":{"x":[0.167],"y":[0.167]},"t":6,"s":[0]},{"t":16,"s":[100]}]},"o":{"a":0,"k":0},"m":1,"nm":"Trim Paths 1","hd":false}],"ip":6,"op":46,"st":0,"bm":0},{"ddd":0,"ind":9,"ty":4,"nm":"Layer 11","sr":1,"ks":{"o":{"a":0,"k":100},"r":{"a":0,"k":0},"p":{"a":1,"k":[{"i":{"x":0.251,"y":1},"o":{"x":0.333,"y":0},"t":0,"s":[287.992,205.649,0],"to":[0,-1.667,0],"ti":[0,0,0]},{"i":{"x":0.667,"y":1},"o":{"x":0.792,"y":0},"t":10,"s":[287.992,195.649,0],"to":[0,0,0],"ti":[0,-1.667,0]},{"t":20,"s":[287.992,205.649,0]}]},"a":{"a":0,"k":[287.992,205.649,0]},"s":{"a":0,"k":[100,100,100]}},"ao":0,"shapes":[{"ty":"gr","it":[{"ind":0,"ty":"sh","ks":{"a":0,"k":{"i":[[0,0],[0,0]],"o":[[0,0],[0,0]],"v":[[19.579,-19.579],[-19.579,19.579]],"c":false}},"nm":"Path 1","hd":false},{"ty":"st","c":{"a":0,"k":[0.4,0.561,0.518]},"o":{"a":0,"k":100},"w":{"a":0,"k":15},"lc":2,"lj":2,"bm":0,"nm":"Stroke 1","hd":false},{"ty":"tr","p":{"a":0,"k":[138.333,205.649]},"a":{"a":0,"k":[0,0]},"s":{"a":0,"k":[100,100]},"r":{"a":0,"k":0},"o":{"a":0,"k":100},"sk":{"a":0,"k":0},"sa":{"a":0,"k":0},"nm":"Transform"}],"nm":"Group 1","bm":0,"hd":false},{"ty":"gr","it":[{"ind":0,"ty":"sh","ks":{"a":0,"k":{"i":[[0,0],[0,0]],"o":[[0,0],[0,0]],"v":[[19.579,19.579],[-19.579,-19.579]],"c":false}},"nm":"Path 1","hd":false},{"ty":"st","c":{"a":0,"k":[0.4,0.561,0.518]},"o":{"a":0,"k":100},"w":{"a":0,"k":15},"lc":2,"lj":2,"bm":0,"nm":"Stroke 1","hd":false},{"ty":"tr","p":{"a":0,"k":[437.65,205.649]},"a":{"a":0,"k":[0,0]},"s":{"a":0,"k":[100,100]},"r":{"a":0,"k":0},"o":{"a":0,"k":100},"sk":{"a":0,"k":0},"sa":{"a":0,"k":0},"nm":"Transform"}],"nm":"Group 2","bm":0,"hd":false},{"ty":"tm","s":{"a":0,"k":0},"e":{"a":1,"k":[{"i":{"x":[0.667],"y":[1]},"o":{"x":[0.167],"y":[0.167]},"t":6,"s":[0]},{"t":16,"s":[100]}]},"o":{"a":0,"k":0},"m":1,"nm":"Trim Paths 1","hd":false}],"ip":6,"op":46,"st":0,"bm":0},{"ddd":0,"ind":10,"ty":4,"nm":"Layer 10","sr":1,"ks":{"o":{"a":0,"k":100},"r":{"a":0,"k":0},"p":{"a":1,"k":[{"i":{"x":0.251,"y":1},"o":{"x":0.333,"y":0},"t":0,"s":[287.992,267.638,0],"to":[0,-4.833,0],"ti":[0,0,0]},{"i":{"x":0.667,"y":1},"o":{"x":0.792,"y":0},"t":10,"s":[287.992,238.638,0],"to":[0,0,0],"ti":[0,-4.833,0]},{"t":20,"s":[287.992,267.638,0]}]},"a":{"a":0,"k":[0,0,0]},"s":{"a":0,"k":[100,100,100]}},"ao":0,"shapes":[{"ty":"gr","it":[{"ind":0,"ty":"sh","ks":{"a":0,"k":{"i":[[0,0],[0,0]],"o":[[0,0],[0,0]],"v":[[0,27.686],[0,-27.686]],"c":false}},"nm":"Path 1","hd":false},{"ty":"st","c":{"a":0,"k":[0.4,0.561,0.518]},"o":{"a":0,"k":100},"w":{"a":0,"k":15},"lc":2,"lj":2,"bm":0,"nm":"Stroke 1","hd":false},{"ty":"tr","p":{"a":0,"k":[0,0]},"a":{"a":0,"k":[0,0]},"s":{"a":0,"k":[100,100]},"r":{"a":0,"k":0},"o":{"a":0,"k":100},"sk":{"a":0,"k":0},"sa":{"a":0,"k":0},"nm":"Transform"}],"nm":"Group 1","bm":0,"hd":false},{"ty":"tm","s":{"a":0,"k":0},"e":{"a":1,"k":[{"i":{"x":[0.667],"y":[1]},"o":{"x":[0.167],"y":[0.167]},"t":6,"s":[0]},{"t":16,"s":[100]}]},"o":{"a":0,"k":0},"m":1,"nm":"Trim Paths 1","hd":false}],"ip":6,"op":46,"st":0,"bm":0},{"ddd":0,"ind":11,"ty":4,"nm":"Layer 3","sr":1,"ks":{"o":{"a":0,"k":100},"r":{"a":0,"k":0},"p":{"a":0,"k":[92.4,137.015,0]},"a":{"a":0,"k":[0,0,0]},"s":{"a":0,"k":[100,100,100]}},"ao":0,"shapes":[{"ty":"gr","it":[{"ind":0,"ty":"sh","ks":{"a":0,"k":{"i":[[0,0],[0,0]],"o":[[0,0],[0,0]],"v":[[25.609,-10.613],[-25.609,10.613]],"c":false}},"nm":"Path 1","hd":false},{"ty":"st","c":{"a":0,"k":[0.4,0.561,0.518]},"o":{"a":0,"k":100},"w":{"a":0,"k":15},"lc":2,"lj":2,"bm":0,"nm":"Stroke 1","hd":false},{"ty":"tr","p":{"a":0,"k":[0,0]},"a":{"a":0,"k":[0,0]},"s":{"a":0,"k":[100,100]},"r":{"a":0,"k":0},"o":{"a":0,"k":100},"sk":{"a":0,"k":0},"sa":{"a":0,"k":0},"nm":"Transform"}],"nm":"Group 1","bm":0,"hd":false},{"ty":"tm","s":{"a":1,"k":[{"i":{"x":[0.833],"y":[0.833]},"o":{"x":[0.333],"y":[0]},"t":0,"s":[0]},{"t":10,"s":[100]}]},"e":{"a":0,"k":100},"o":{"a":0,"k":0},"m":1,"nm":"Trim Paths 1","hd":false}],"ip":0,"op":46,"st":0,"bm":0},{"ddd":0,"ind":12,"ty":4,"nm":"Layer 5","sr":1,"ks":{"o":{"a":0,"k":100},"r":{"a":0,"k":0},"p":{"a":0,"k":[483.554,137.001,0]},"a":{"a":0,"k":[0,0,0]},"s":{"a":0,"k":[100,100,100]}},"ao":0,"shapes":[{"ty":"gr","it":[{"ind":0,"ty":"sh","ks":{"a":0,"k":{"i":[[0,0],[0,0]],"o":[[0,0],[0,0]],"v":[[25.58,10.599],[-25.58,-10.599]],"c":false}},"nm":"Path 1","hd":false},{"ty":"st","c":{"a":0,"k":[0.4,0.561,0.518]},"o":{"a":0,"k":100},"w":{"a":0,"k":15},"lc":2,"lj":2,"bm":0,"nm":"Stroke 1","hd":false},{"ty":"tr","p":{"a":0,"k":[0,0]},"a":{"a":0,"k":[0,0]},"s":{"a":0,"k":[100,100]},"r":{"a":0,"k":0},"o":{"a":0,"k":100},"sk":{"a":0,"k":0},"sa":{"a":0,"k":0},"nm":"Transform"}],"nm":"Group 1","bm":0,"hd":false},{"ty":"tm","s":{"a":1,"k":[{"i":{"x":[0.833],"y":[0.833]},"o":{"x":[0.333],"y":[0]},"t":0,"s":[0]},{"t":10,"s":[100]}]},"e":{"a":0,"k":100},"o":{"a":0,"k":0},"m":1,"nm":"Trim Paths 1","hd":false}],"ip":0,"op":46,"st":0,"bm":0},{"ddd":0,"ind":13,"ty":4,"nm":"Layer 6","sr":1,"ks":{"o":{"a":0,"k":100},"r":{"a":0,"k":0},"p":{"a":1,"k":[{"i":{"x":0.251,"y":1},"o":{"x":0.333,"y":0},"t":0,"s":[206.982,251.568,0],"to":[0,-3.833,0],"ti":[0,0,0]},{"i":{"x":0.667,"y":1},"o":{"x":0.792,"y":0},"t":10,"s":[206.982,228.568,0],"to":[0,0,0],"ti":[0,-3.833,0]},{"t":20,"s":[206.982,251.568,0]}]},"a":{"a":0,"k":[0,0,0]},"s":{"a":0,"k":[100,100,100]}},"ao":0,"shapes":[{"ty":"gr","it":[{"ind":0,"ty":"sh","ks":{"a":0,"k":{"i":[[0,0],[0,0]],"o":[[0,0],[0,0]],"v":[[10.599,-25.595],[-10.599,25.595]],"c":false}},"nm":"Path 1","hd":false},{"ty":"st","c":{"a":0,"k":[0.4,0.561,0.518]},"o":{"a":0,"k":100},"w":{"a":0,"k":15},"lc":2,"lj":2,"bm":0,"nm":"Stroke 1","hd":false},{"ty":"tr","p":{"a":0,"k":[0,0]},"a":{"a":0,"k":[0,0]},"s":{"a":0,"k":[100,100]},"r":{"a":0,"k":0},"o":{"a":0,"k":100},"sk":{"a":0,"k":0},"sa":{"a":0,"k":0},"nm":"Transform"}],"nm":"Group 1","bm":0,"hd":false},{"ty":"tm","s":{"a":1,"k":[{"i":{"x":[0.833],"y":[0.833]},"o":{"x":[0.333],"y":[0]},"t":0,"s":[0]},{"t":10,"s":[100]}]},"e":{"a":0,"k":100},"o":{"a":0,"k":0},"m":1,"nm":"Trim Paths 1","hd":false}],"ip":0,"op":46,"st":0,"bm":0},{"ddd":0,"ind":14,"ty":4,"nm":"Layer 4","sr":1,"ks":{"o":{"a":0,"k":100},"r":{"a":0,"k":0},"p":{"a":1,"k":[{"i":{"x":0.251,"y":1},"o":{"x":0.333,"y":0},"t":0,"s":[369.001,251.554,0],"to":[0,-3.833,0],"ti":[0,0,0]},{"i":{"x":0.667,"y":1},"o":{"x":0.792,"y":0},"t":10,"s":[369.001,228.554,0],"to":[0,0,0],"ti":[0,-3.833,0]},{"t":20,"s":[369.001,251.554,0]}]},"a":{"a":0,"k":[0,0,0]},"s":{"a":0,"k":[100,100,100]}},"ao":0,"shapes":[{"ty":"gr","it":[{"ind":0,"ty":"sh","ks":{"a":0,"k":{"i":[[0,0],[0,0]],"o":[[0,0],[0,0]],"v":[[10.599,25.58],[-10.599,-25.58]],"c":false}},"nm":"Path 1","hd":false},{"ty":"st","c":{"a":0,"k":[0.4,0.561,0.518]},"o":{"a":0,"k":100},"w":{"a":0,"k":15},"lc":2,"lj":2,"bm":0,"nm":"Stroke 1","hd":false},{"ty":"tr","p":{"a":0,"k":[0,0]},"a":{"a":0,"k":[0,0]},"s":{"a":0,"k":[100,100]},"r":{"a":0,"k":0},"o":{"a":0,"k":100},"sk":{"a":0,"k":0},"sa":{"a":0,"k":0},"nm":"Transform"}],"nm":"Group 1","bm":0,"hd":false},{"ty":"tm","s":{"a":1,"k":[{"i":{"x":[0.833],"y":[0.833]},"o":{"x":[0.333],"y":[0]},"t":0,"s":[0]},{"t":10,"s":[100]}]},"e":{"a":0,"k":100},"o":{"a":0,"k":0},"m":1,"nm":"Trim Paths 1","hd":false}],"ip":0,"op":46,"st":0,"bm":0},{"ddd":0,"ind":15,"ty":4,"nm":"Layer 2","sr":1,"ks":{"o":{"a":0,"k":100},"r":{"a":0,"k":0},"p":{"a":1,"k":[{"i":{"x":0.251,"y":1},"o":{"x":0.333,"y":0},"t":0,"s":[287.992,205.649,0],"to":[0,-1.667,0],"ti":[0,0,0]},{"i":{"x":0.667,"y":1},"o":{"x":0.792,"y":0},"t":10,"s":[287.992,195.649,0],"to":[0,0,0],"ti":[0,-1.667,0]},{"t":20,"s":[287.992,205.649,0]}]},"a":{"a":0,"k":[287.992,205.649,0]},"s":{"a":0,"k":[100,100,100]}},"ao":0,"shapes":[{"ty":"gr","it":[{"ind":0,"ty":"sh","ks":{"a":0,"k":{"i":[[0,0],[0,0]],"o":[[0,0],[0,0]],"v":[[19.579,-19.579],[-19.579,19.579]],"c":false}},"nm":"Path 1","hd":false},{"ty":"st","c":{"a":0,"k":[0.4,0.561,0.518]},"o":{"a":0,"k":100},"w":{"a":0,"k":15},"lc":2,"lj":2,"bm":0,"nm":"Stroke 1","hd":false},{"ty":"tr","p":{"a":0,"k":[138.333,205.649]},"a":{"a":0,"k":[0,0]},"s":{"a":0,"k":[100,100]},"r":{"a":0,"k":0},"o":{"a":0,"k":100},"sk":{"a":0,"k":0},"sa":{"a":0,"k":0},"nm":"Transform"}],"nm":"Group 1","bm":0,"hd":false},{"ty":"gr","it":[{"ind":0,"ty":"sh","ks":{"a":0,"k":{"i":[[0,0],[0,0]],"o":[[0,0],[0,0]],"v":[[19.579,19.579],[-19.579,-19.579]],"c":false}},"nm":"Path 1","hd":false},{"ty":"st","c":{"a":0,"k":[0.4,0.561,0.518]},"o":{"a":0,"k":100},"w":{"a":0,"k":15},"lc":2,"lj":2,"bm":0,"nm":"Stroke 1","hd":false},{"ty":"tr","p":{"a":0,"k":[437.65,205.649]},"a":{"a":0,"k":[0,0]},"s":{"a":0,"k":[100,100]},"r":{"a":0,"k":0},"o":{"a":0,"k":100},"sk":{"a":0,"k":0},"sa":{"a":0,"k":0},"nm":"Transform"}],"nm":"Group 2","bm":0,"hd":false},{"ty":"tm","s":{"a":1,"k":[{"i":{"x":[0.833],"y":[0.833]},"o":{"x":[0.333],"y":[0]},"t":0,"s":[0]},{"t":10,"s":[100]}]},"e":{"a":0,"k":100},"o":{"a":0,"k":0},"m":1,"nm":"Trim Paths 1","hd":false}],"ip":0,"op":46,"st":0,"bm":0},{"ddd":0,"ind":16,"ty":4,"nm":"Layer 1","sr":1,"ks":{"o":{"a":0,"k":100},"r":{"a":0,"k":0},"p":{"a":1,"k":[{"i":{"x":0.251,"y":1},"o":{"x":0.333,"y":0},"t":0,"s":[287.992,267.638,0],"to":[0,-4.833,0],"ti":[0,0,0]},{"i":{"x":0.667,"y":1},"o":{"x":0.792,"y":0},"t":10,"s":[287.992,238.638,0],"to":[0,0,0],"ti":[0,-4.833,0]},{"t":20,"s":[287.992,267.638,0]}]},"a":{"a":0,"k":[0,0,0]},"s":{"a":0,"k":[100,100,100]}},"ao":0,"shapes":[{"ty":"gr","it":[{"ind":0,"ty":"sh","ks":{"a":0,"k":{"i":[[0,0],[0,0]],"o":[[0,0],[0,0]],"v":[[0,27.686],[0,-27.686]],"c":false}},"nm":"Path 1","hd":false},{"ty":"st","c":{"a":0,"k":[0.4,0.561,0.518]},"o":{"a":0,"k":100},"w":{"a":0,"k":15},"lc":2,"lj":2,"bm":0,"nm":"Stroke 1","hd":false},{"ty":"tr","p":{"a":0,"k":[0,0]},"a":{"a":0,"k":[0,0]},"s":{"a":0,"k":[100,100]},"r":{"a":0,"k":0},"o":{"a":0,"k":100},"sk":{"a":0,"k":0},"sa":{"a":0,"k":0},"nm":"Transform"}],"nm":"Group 1","bm":0,"hd":false},{"ty":"tm","s":{"a":1,"k":[{"i":{"x":[0.833],"y":[0.833]},"o":{"x":[0.333],"y":[0]},"t":0,"s":[0]},{"t":10,"s":[100]}]},"e":{"a":0,"k":100},"o":{"a":0,"k":0},"m":1,"nm":"Trim Paths 1","hd":false}],"ip":0,"op":46,"st":0,"bm":0}],"markers":[]}